setup.py
pyrtorrent/__init__.py
pyrtorrent/rtorrent.py
pyrtorrent/torrent.py
pyrtorrent.egg-info/PKG-INFO
pyrtorrent.egg-info/SOURCES.txt
pyrtorrent.egg-info/dependency_links.txt
pyrtorrent.egg-info/top_level.txt