Metadata-Version: 1.1
Name: pyrtorrent
Version: 0.1.0
Summary: rTorrent xmlrpc wrapper
Home-page: https://github.com/marhag87/pyrtorrent
Author: marhag87
Author-email: marhag87@gmail.com
License: WTFPL
Platform: UNKNOWN
Classifier: Development Status :: 4 - Beta
Classifier: Intended Audience :: Developers
Classifier: Programming Language :: Python :: 3
